{
  "session_id": "10900_2747",
  "job_id": "44cdca32-786d-4fc9-b0cf-b3991122049b",
  "timestamp": "2025-11-19T10:29:53.840388",
  "events": [
    {
      "session_id": "10900_2747",
      "event_id": "10900_2747_qq-1472",
      "timestamp": "2006-05-15 16:48:37",
      "action_type": "QUERY",
      "content": "ny lottery",
      "cognitive_label": "PoorScent",
      "analyst_label": "FollowingScent",
      "analyst_justification": "Analysis error: Invalid control character at: line 5 column 23 (char 97)",
      "critic_label": "PoorScent",
      "critic_agreement": "disagree",
      "critic_justification": "The query 'ny lottery...' lacks specificity and may not yield desirable results, indicating a poor scent rather than a strong targeted intent. A valid FollowingScent label would require a clearer, more focused query.",
      "judge_justification": "Judge parsing failed, using critic decision. Error: Invalid control character at: line 5 column 23 (char 98)",
      "confidence_score": 0.68,
      "disagreement_score": 1.0179530039429665,
      "flagged_for_review": true,
      "user_override": false,
      "override_version": 1,
      "override_timestamp": "2025-11-19T10:31:06.699658"
    },
    {
      "session_id": "10900_2747",
      "event_id": "10900_2747_qq-1472_serp",
      "timestamp": "2006-05-15 16:48:37",
      "action_type": "SERP_VIEW",
      "content": "Viewed 10 results: ny state lottery, new york lottery results ny lottery org, new york lottery results ny lottery org (+7 more)",
      "cognitive_label": "PoorScent",
      "analyst_label": "FollowingScent",
      "analyst_justification": "Analysis error: Invalid control character at: line 5 column 23 (char 97)",
      "critic_label": "PoorScent",
      "critic_agreement": "disagree",
      "critic_justification": "Viewing a list of results that may not align with a clear query indicates a lack of promising scent. The analyst assumes intent where there may be confusion or dissatisfaction with the initial query.",
      "judge_justification": "Judge parsing failed, using critic decision. Error: Invalid control character at: line 5 column 23 (char 98)",
      "confidence_score": 0.6400000000000001,
      "disagreement_score": 0.9325683414936066,
      "flagged_for_review": true,
      "user_override": false,
      "override_version": 1,
      "override_timestamp": "2025-11-19T10:31:06.699664"
    },
    {
      "session_id": "10900_2747",
      "event_id": "10900_2747_qq-1472_cd-8732",
      "timestamp": "2006-05-15 16:48:37",
      "action_type": "CLICK",
      "content": "new york lottery results ny lottery org",
      "cognitive_label": "PoorScent",
      "analyst_label": "FollowingScent",
      "analyst_justification": "Analysis error: Invalid control character at: line 5 column 23 (char 97)",
      "critic_label": "PoorScent",
      "critic_agreement": "disagree",
      "critic_justification": "Clicking on a result that is part of a poorly defined query suggests that the user is not finding the right information. A FollowingScent label requires a strong cue of intent, which is absent here.",
      "judge_justification": "Judge parsing failed, using critic decision. Error: Invalid control character at: line 5 column 23 (char 98)",
      "confidence_score": 0.68,
      "disagreement_score": 0.953377541899681,
      "flagged_for_review": true,
      "user_override": false,
      "override_version": 1,
      "override_timestamp": "2025-11-19T10:31:06.699667"
    },
    {
      "session_id": "10900_2747",
      "event_id": "10900_2747_qq-1415",
      "timestamp": "2006-05-15 17:12:02",
      "action_type": "QUERY",
      "content": "chase manhattan bank",
      "cognitive_label": "PoorScent",
      "analyst_label": "FollowingScent",
      "analyst_justification": "Analysis error: Invalid control character at: line 5 column 23 (char 97)",
      "critic_label": "PoorScent",
      "critic_agreement": "disagree",
      "critic_justification": "The query 'chase manhattan bank...' appears vague and does not target a specific need, indicating a poor scent rather than a focused search. FollowingScent should represent clear intent, which is not present.",
      "judge_justification": "Judge parsing failed, using critic decision. Error: Invalid control character at: line 5 column 23 (char 98)",
      "confidence_score": 0.6400000000000001,
      "disagreement_score": 0.9735420346260071,
      "flagged_for_review": true,
      "user_override": false,
      "override_version": 1,
      "override_timestamp": "2025-11-19T10:31:06.699670"
    },
    {
      "session_id": "10900_2747",
      "event_id": "10900_2747_qq-1415_serp",
      "timestamp": "2006-05-15 17:12:02",
      "action_type": "SERP_VIEW",
      "content": "Viewed 10 results: credit card mortgage banking auto chase online chase com, credit card mortgage banking auto chase online chase com, credit card mortgage banking auto chase online chase com (+7 more)",
      "cognitive_label": "PoorScent",
      "analyst_label": "FollowingScent",
      "analyst_justification": "Analysis error: Invalid control character at: line 5 column 23 (char 97)",
      "critic_label": "PoorScent",
      "critic_agreement": "disagree",
      "critic_justification": "The viewed results from a vague query suggest the user is not pursuing a defined path or scent. The repeated nature of results indicates that the user is not finding relevant information and lacks strong intent.",
      "judge_justification": "Judge parsing failed, using critic decision. Error: Invalid control character at: line 5 column 23 (char 98)",
      "confidence_score": 0.6400000000000001,
      "disagreement_score": 0.9901338055729866,
      "flagged_for_review": true,
      "user_override": false,
      "override_version": 1,
      "override_timestamp": "2025-11-19T10:31:06.699672"
    },
    {
      "session_id": "10900_2747",
      "event_id": "10900_2747_qq-1415_cd-8643",
      "timestamp": "2006-05-15 17:12:02",
      "action_type": "CLICK",
      "content": "credit card mortgage banking auto chase online chase com",
      "cognitive_label": "PoorScent",
      "analyst_label": "FollowingScent",
      "analyst_justification": "Analysis error: Invalid control character at: line 5 column 23 (char 97)",
      "critic_label": "PoorScent",
      "critic_agreement": "disagree",
      "critic_justification": "Clicking on a generic link without a clear information need points to a lack of promising scent. A FollowingScent label is inappropriate here as it implies intentionality that is not evident in this action.",
      "judge_justification": "Judge parsing failed, using critic decision. Error: Invalid control character at: line 5 column 23 (char 98)",
      "confidence_score": 0.68,
      "disagreement_score": 1.0067874275147914,
      "flagged_for_review": true,
      "user_override": false,
      "override_version": 1,
      "override_timestamp": "2025-11-19T10:31:06.699674"
    }
  ],
  "agent_interactions": [
    {
      "step": 1,
      "agent": "analyst",
      "status": "completed",
      "elapsed_time": 25.621881008148193,
      "decisions": [
        {
          "event_id": "10900_2747_qq-1472",
          "label": "FollowingScent",
          "justification": "Analysis error: Invalid control character at: line 5 column 23 (char 97)",
          "confidence": 0.5
        },
        {
          "event_id": "10900_2747_qq-1472_serp",
          "label": "FollowingScent",
          "justification": "Analysis error: Invalid control character at: line 5 column 23 (char 97)",
          "confidence": 0.5
        },
        {
          "event_id": "10900_2747_qq-1472_cd-8732",
          "label": "FollowingScent",
          "justification": "Analysis error: Invalid control character at: line 5 column 23 (char 97)",
          "confidence": 0.5
        },
        {
          "event_id": "10900_2747_qq-1415",
          "label": "FollowingScent",
          "justification": "Analysis error: Invalid control character at: line 5 column 23 (char 97)",
          "confidence": 0.5
        },
        {
          "event_id": "10900_2747_qq-1415_serp",
          "label": "FollowingScent",
          "justification": "Analysis error: Invalid control character at: line 5 column 23 (char 97)",
          "confidence": 0.5
        },
        {
          "event_id": "10900_2747_qq-1415_cd-8643",
          "label": "FollowingScent",
          "justification": "Analysis error: Invalid control character at: line 5 column 23 (char 97)",
          "confidence": 0.5
        }
      ]
    },
    {
      "step": 2,
      "agent": "critic",
      "status": "completed",
      "elapsed_time": 7.8377602100372314,
      "decisions": [
        {
          "event_id": "Event 1",
          "agreement": "disagree",
          "label": "PoorScent",
          "justification": "The query 'ny lottery...' lacks specificity and may not yield desirable results, indicating a poor scent rather than a strong targeted intent. A valid FollowingScent label would require a clearer, more focused query.",
          "confidence": 0.85
        },
        {
          "event_id": "Event 2",
          "agreement": "disagree",
          "label": "PoorScent",
          "justification": "Viewing a list of results that may not align with a clear query indicates a lack of promising scent. The analyst assumes intent where there may be confusion or dissatisfaction with the initial query.",
          "confidence": 0.8
        },
        {
          "event_id": "Event 3",
          "agreement": "disagree",
          "label": "PoorScent",
          "justification": "Clicking on a result that is part of a poorly defined query suggests that the user is not finding the right information. A FollowingScent label requires a strong cue of intent, which is absent here.",
          "confidence": 0.85
        },
        {
          "event_id": "Event 4",
          "agreement": "disagree",
          "label": "PoorScent",
          "justification": "The query 'chase manhattan bank...' appears vague and does not target a specific need, indicating a poor scent rather than a focused search. FollowingScent should represent clear intent, which is not present.",
          "confidence": 0.8
        },
        {
          "event_id": "Event 5",
          "agreement": "disagree",
          "label": "PoorScent",
          "justification": "The viewed results from a vague query suggest the user is not pursuing a defined path or scent. The repeated nature of results indicates that the user is not finding relevant information and lacks strong intent.",
          "confidence": 0.8
        },
        {
          "event_id": "Event 6",
          "agreement": "disagree",
          "label": "PoorScent",
          "justification": "Clicking on a generic link without a clear information need points to a lack of promising scent. A FollowingScent label is inappropriate here as it implies intentionality that is not evident in this action.",
          "confidence": 0.85
        }
      ]
    },
    {
      "step": 3,
      "agent": "judge",
      "status": "completed",
      "elapsed_time": 39.24724578857422,
      "decisions": [
        {
          "event_id": "Event 1",
          "final_label": "PoorScent",
          "justification": "Judge parsing failed, using critic decision. Error: Invalid control character at: line 5 column 23 (char 98)",
          "confidence": 0.68,
          "flag_for_review": true,
          "disagreement_score": 0.5
        },
        {
          "event_id": "Event 2",
          "final_label": "PoorScent",
          "justification": "Judge parsing failed, using critic decision. Error: Invalid control character at: line 5 column 23 (char 98)",
          "confidence": 0.6400000000000001,
          "flag_for_review": true,
          "disagreement_score": 0.5
        },
        {
          "event_id": "Event 3",
          "final_label": "PoorScent",
          "justification": "Judge parsing failed, using critic decision. Error: Invalid control character at: line 5 column 23 (char 98)",
          "confidence": 0.68,
          "flag_for_review": true,
          "disagreement_score": 0.5
        },
        {
          "event_id": "Event 4",
          "final_label": "PoorScent",
          "justification": "Judge parsing failed, using critic decision. Error: Invalid control character at: line 5 column 23 (char 98)",
          "confidence": 0.6400000000000001,
          "flag_for_review": true,
          "disagreement_score": 0.5
        },
        {
          "event_id": "Event 5",
          "final_label": "PoorScent",
          "justification": "Judge parsing failed, using critic decision. Error: Invalid control character at: line 5 column 23 (char 98)",
          "confidence": 0.6400000000000001,
          "flag_for_review": true,
          "disagreement_score": 0.5
        },
        {
          "event_id": "Event 6",
          "final_label": "PoorScent",
          "justification": "Judge parsing failed, using critic decision. Error: Invalid control character at: line 5 column 23 (char 98)",
          "confidence": 0.68,
          "flag_for_review": true,
          "disagreement_score": 0.5
        }
      ]
    }
  ],
  "num_events": 6,
  "flagged_for_review": true,
  "max_disagreement": 1.0179530039429665
}