{
  "session_id": "12211_3029",
  "job_id": "44cdca32-786d-4fc9-b0cf-b3991122049b",
  "timestamp": "2025-11-19T14:37:40.495088",
  "events": [
    {
      "session_id": "12211_3029",
      "event_id": "12211_3029_qq-1417",
      "timestamp": "2006-04-26 19:25:23",
      "action_type": "QUERY",
      "content": "myspace",
      "cognitive_label": "PoorScent",
      "analyst_label": "FollowingScent",
      "analyst_justification": "Analysis error: Invalid control character at: line 5 column 23 (char 97)",
      "critic_label": "PoorScent",
      "critic_agreement": "disagree",
      "critic_justification": "The query 'myspace...' does not indicate a clear and targeted intent, especially given that it is potentially incomplete or malformed. This suggests a lack of promising information scent, leading to an ineffective search attempt.",
      "judge_justification": "Judge parsing failed, using critic decision. Error: Invalid control character at: line 5 column 23 (char 98)",
      "confidence_score": 0.68,
      "disagreement_score": 0.9847663566470146,
      "flagged_for_review": true,
      "user_override": false,
      "override_version": 1,
      "override_timestamp": "2025-11-19T14:38:21.243627"
    },
    {
      "session_id": "12211_3029",
      "event_id": "12211_3029_qq-1417_serp",
      "timestamp": "2006-04-26 19:25:23",
      "action_type": "SERP_VIEW",
      "content": "Viewed 10 results: featured content on myspace, featured content on myspace, www pimp myspace ca (+7 more)",
      "cognitive_label": "PoorScent",
      "analyst_label": "FollowingScent",
      "analyst_justification": "Analysis error: Invalid control character at: line 5 column 23 (char 97)",
      "critic_label": "PoorScent",
      "critic_agreement": "disagree",
      "critic_justification": "Viewing results that are all centered around 'myspace' does not indicate a strong attempt to engage with the content. The repetition of 'featured content on myspace' suggests that the results may not be relevant or satisfying, indicating a lack of strong information scent.",
      "judge_justification": "Judge parsing failed, using critic decision. Error: Invalid control character at: line 5 column 23 (char 98)",
      "confidence_score": 0.6400000000000001,
      "disagreement_score": 1.0071175277233124,
      "flagged_for_review": true,
      "user_override": false,
      "override_version": 1,
      "override_timestamp": "2025-11-19T14:38:21.243646"
    },
    {
      "session_id": "12211_3029",
      "event_id": "12211_3029_qq-1417_cd-699",
      "timestamp": "2006-04-26 19:25:23",
      "action_type": "CLICK",
      "content": "featured content on myspace",
      "cognitive_label": "LeavingPatch",
      "analyst_label": "FollowingScent",
      "analyst_justification": "Analysis error: Invalid control character at: line 5 column 23 (char 97)",
      "critic_label": "LeavingPatch",
      "critic_agreement": "disagree",
      "critic_justification": "Clicking on 'featured content on myspace...' could indicate an attempt to find more information, but it should be viewed in the context of the previous events, which show a pattern of dissatisfaction. If the user has been repeatedly exposed to poor results, this click may not represent a successful search but rather a last-ditch effort before abandoning the search altogether.",
      "judge_justification": "Judge parsing failed, using critic decision. Error: Invalid control character at: line 5 column 23 (char 98)",
      "confidence_score": 0.6000000000000001,
      "disagreement_score": 1.0043312691152095,
      "flagged_for_review": true,
      "user_override": false,
      "override_version": 1,
      "override_timestamp": "2025-11-19T14:38:21.243652"
    }
  ],
  "agent_interactions": [
    {
      "step": 1,
      "agent": "analyst",
      "status": "completed",
      "elapsed_time": 20.7660129070282,
      "decisions": [
        {
          "event_id": "12211_3029_qq-1417",
          "label": "FollowingScent",
          "justification": "Analysis error: Invalid control character at: line 5 column 23 (char 97)",
          "confidence": 0.5
        },
        {
          "event_id": "12211_3029_qq-1417_serp",
          "label": "FollowingScent",
          "justification": "Analysis error: Invalid control character at: line 5 column 23 (char 97)",
          "confidence": 0.5
        },
        {
          "event_id": "12211_3029_qq-1417_cd-699",
          "label": "FollowingScent",
          "justification": "Analysis error: Invalid control character at: line 5 column 23 (char 97)",
          "confidence": 0.5
        }
      ]
    },
    {
      "step": 2,
      "agent": "critic",
      "status": "completed",
      "elapsed_time": 6.436674118041992,
      "decisions": [
        {
          "event_id": "1",
          "agreement": "disagree",
          "label": "PoorScent",
          "justification": "The query 'myspace...' does not indicate a clear and targeted intent, especially given that it is potentially incomplete or malformed. This suggests a lack of promising information scent, leading to an ineffective search attempt.",
          "confidence": 0.85
        },
        {
          "event_id": "2",
          "agreement": "disagree",
          "label": "PoorScent",
          "justification": "Viewing results that are all centered around 'myspace' does not indicate a strong attempt to engage with the content. The repetition of 'featured content on myspace' suggests that the results may not be relevant or satisfying, indicating a lack of strong information scent.",
          "confidence": 0.8
        },
        {
          "event_id": "3",
          "agreement": "disagree",
          "label": "LeavingPatch",
          "justification": "Clicking on 'featured content on myspace...' could indicate an attempt to find more information, but it should be viewed in the context of the previous events, which show a pattern of dissatisfaction. If the user has been repeatedly exposed to poor results, this click may not represent a successful search but rather a last-ditch effort before abandoning the search altogether.",
          "confidence": 0.75
        }
      ]
    },
    {
      "step": 3,
      "agent": "judge",
      "status": "completed",
      "elapsed_time": 13.325664043426514,
      "decisions": [
        {
          "event_id": "1",
          "final_label": "PoorScent",
          "justification": "Judge parsing failed, using critic decision. Error: Invalid control character at: line 5 column 23 (char 98)",
          "confidence": 0.68,
          "flag_for_review": true,
          "disagreement_score": 0.5
        },
        {
          "event_id": "2",
          "final_label": "PoorScent",
          "justification": "Judge parsing failed, using critic decision. Error: Invalid control character at: line 5 column 23 (char 98)",
          "confidence": 0.6400000000000001,
          "flag_for_review": true,
          "disagreement_score": 0.5
        },
        {
          "event_id": "3",
          "final_label": "LeavingPatch",
          "justification": "Judge parsing failed, using critic decision. Error: Invalid control character at: line 5 column 23 (char 98)",
          "confidence": 0.6000000000000001,
          "flag_for_review": true,
          "disagreement_score": 0.5
        }
      ]
    }
  ],
  "num_events": 3,
  "flagged_for_review": true,
  "max_disagreement": 1.0071175277233124
}