{
  "session_id": "14551_3379",
  "job_id": "44cdca32-786d-4fc9-b0cf-b3991122049b",
  "timestamp": "2025-11-19T20:23:49.726752",
  "events": [
    {
      "session_id": "14551_3379",
      "event_id": "14551_3379_qq-502",
      "timestamp": "2006-05-14 22:11:00",
      "action_type": "QUERY",
      "content": "yahoo.com",
      "cognitive_label": "PoorScent",
      "analyst_label": "FollowingScent",
      "analyst_justification": "Analysis error: Invalid control character at: line 5 column 23 (char 96)",
      "critic_label": "PoorScent",
      "critic_agreement": "disagree",
      "critic_justification": "The action of issuing a query without any clicks or engagement suggests that the user did not find promising information. The label 'FollowingScent' implies a targeted and engaged search, which is inconsistent with the context of an invalid control character error. This indicates a possible lack of relevant information or clarity in the search results.",
      "judge_justification": "Judge parsing failed, using critic decision. Error: Invalid control character at: line 5 column 23 (char 97)",
      "confidence_score": 0.68,
      "disagreement_score": 0.9134239912033081,
      "flagged_for_review": true,
      "user_override": false,
      "override_version": 1,
      "override_timestamp": "2025-11-19T20:24:29.431552"
    },
    {
      "session_id": "14551_3379",
      "event_id": "14551_3379_qq-502_serp",
      "timestamp": "2006-05-14 22:11:00",
      "action_type": "SERP_VIEW",
      "content": "Viewed 10 results: yahoo mail, yahoo world, yahoo japan (+7 more)",
      "cognitive_label": "PoorScent",
      "analyst_label": "FollowingScent",
      "analyst_justification": "Analysis error: Invalid control character at: line 5 column 23 (char 96)",
      "critic_label": "PoorScent",
      "critic_agreement": "disagree",
      "critic_justification": "Viewing search results without engagement (clicks) indicates that the user did not find the presented options appealing or useful enough to pursue further. The label 'FollowingScent' suggests a strong intent to engage, which contradicts the user's apparent lack of interest in the results shown.",
      "judge_justification": "Judge parsing failed, using critic decision. Error: Invalid control character at: line 5 column 23 (char 97)",
      "confidence_score": 0.6400000000000001,
      "disagreement_score": 1.0092311523854733,
      "flagged_for_review": true,
      "user_override": false,
      "override_version": 1,
      "override_timestamp": "2025-11-19T20:24:29.431561"
    },
    {
      "session_id": "14551_3379",
      "event_id": "14551_3379_qq-502_cd-3033",
      "timestamp": "2006-05-14 22:11:00",
      "action_type": "CLICK",
      "content": "yahoo mail",
      "cognitive_label": "PoorScent",
      "analyst_label": "FollowingScent",
      "analyst_justification": "Analysis error: Invalid control character at: line 5 column 23 (char 96)",
      "critic_label": "PoorScent",
      "critic_agreement": "disagree",
      "critic_justification": "Clicking on a result like 'yahoo mail' may not necessarily indicate a strong information scent if the user's overall search experience has been poor up to that point. It is possible that the user clicked out of frustration or habit rather than a clear, targeted intention, which aligns more closely with 'PoorScent' than 'FollowingScent'.",
      "judge_justification": "Judge parsing failed, using critic decision. Error: Invalid control character at: line 5 column 23 (char 97)",
      "confidence_score": 0.6000000000000001,
      "disagreement_score": 0.9982766395434737,
      "flagged_for_review": true,
      "user_override": false,
      "override_version": 1,
      "override_timestamp": "2025-11-19T20:24:29.431566"
    }
  ],
  "agent_interactions": [
    {
      "step": 1,
      "agent": "analyst",
      "status": "completed",
      "elapsed_time": 17.402420043945312,
      "decisions": [
        {
          "event_id": "14551_3379_qq-502",
          "label": "FollowingScent",
          "justification": "Analysis error: Invalid control character at: line 5 column 23 (char 96)",
          "confidence": 0.5
        },
        {
          "event_id": "14551_3379_qq-502_serp",
          "label": "FollowingScent",
          "justification": "Analysis error: Invalid control character at: line 5 column 23 (char 96)",
          "confidence": 0.5
        },
        {
          "event_id": "14551_3379_qq-502_cd-3033",
          "label": "FollowingScent",
          "justification": "Analysis error: Invalid control character at: line 5 column 23 (char 96)",
          "confidence": 0.5
        }
      ]
    },
    {
      "step": 2,
      "agent": "critic",
      "status": "completed",
      "elapsed_time": 6.444236993789673,
      "decisions": [
        {
          "event_id": "Event 1",
          "agreement": "disagree",
          "label": "PoorScent",
          "justification": "The action of issuing a query without any clicks or engagement suggests that the user did not find promising information. The label 'FollowingScent' implies a targeted and engaged search, which is inconsistent with the context of an invalid control character error. This indicates a possible lack of relevant information or clarity in the search results.",
          "confidence": 0.85
        },
        {
          "event_id": "Event 2",
          "agreement": "disagree",
          "label": "PoorScent",
          "justification": "Viewing search results without engagement (clicks) indicates that the user did not find the presented options appealing or useful enough to pursue further. The label 'FollowingScent' suggests a strong intent to engage, which contradicts the user's apparent lack of interest in the results shown.",
          "confidence": 0.8
        },
        {
          "event_id": "Event 3",
          "agreement": "disagree",
          "label": "PoorScent",
          "justification": "Clicking on a result like 'yahoo mail' may not necessarily indicate a strong information scent if the user's overall search experience has been poor up to that point. It is possible that the user clicked out of frustration or habit rather than a clear, targeted intention, which aligns more closely with 'PoorScent' than 'FollowingScent'.",
          "confidence": 0.75
        }
      ]
    },
    {
      "step": 3,
      "agent": "judge",
      "status": "completed",
      "elapsed_time": 15.594658851623535,
      "decisions": [
        {
          "event_id": "Event 1",
          "final_label": "PoorScent",
          "justification": "Judge parsing failed, using critic decision. Error: Invalid control character at: line 5 column 23 (char 97)",
          "confidence": 0.68,
          "flag_for_review": true,
          "disagreement_score": 0.5
        },
        {
          "event_id": "Event 2",
          "final_label": "PoorScent",
          "justification": "Judge parsing failed, using critic decision. Error: Invalid control character at: line 5 column 23 (char 97)",
          "confidence": 0.6400000000000001,
          "flag_for_review": true,
          "disagreement_score": 0.5
        },
        {
          "event_id": "Event 3",
          "final_label": "PoorScent",
          "justification": "Judge parsing failed, using critic decision. Error: Invalid control character at: line 5 column 23 (char 97)",
          "confidence": 0.6000000000000001,
          "flag_for_review": true,
          "disagreement_score": 0.5
        }
      ]
    }
  ],
  "num_events": 3,
  "flagged_for_review": true,
  "max_disagreement": 1.0092311523854733
}