{
  "session_id": "14915_3545",
  "job_id": "44cdca32-786d-4fc9-b0cf-b3991122049b",
  "timestamp": "2025-11-19T22:18:56.650225",
  "events": [
    {
      "session_id": "14915_3545",
      "event_id": "14915_3545_qq-1967",
      "timestamp": "2006-04-22 23:25:48",
      "action_type": "QUERY",
      "content": "tiava",
      "cognitive_label": "PoorScent",
      "analyst_label": "FollowingScent",
      "analyst_justification": "Analysis error: Invalid control character at: line 5 column 23 (char 97)",
      "critic_label": "PoorScent",
      "critic_agreement": "disagree",
      "critic_justification": "The user input 'tiava...' appears to be an incomplete or poorly formed query, indicating a lack of clarity in their information need. The presence of an invalid control character suggests confusion or error rather than a targeted search, which aligns more with PoorScent than FollowingScent.",
      "judge_justification": "Judge parsing failed, using critic decision. Error: Invalid control character at: line 5 column 23 (char 98)",
      "confidence_score": 0.68,
      "disagreement_score": 0.8936943054199218,
      "flagged_for_review": true,
      "user_override": false,
      "override_version": 1,
      "override_timestamp": "2025-11-19T22:20:08.457322"
    },
    {
      "session_id": "14915_3545",
      "event_id": "14915_3545_qq-1967_serp",
      "timestamp": "2006-04-22 23:25:48",
      "action_type": "SERP_VIEW",
      "content": "Viewed 10 results: ti avas girls com nbsp ti avas girls resources and information, free porno movies ti ava com, free porno movies ti ava com (+7 more)",
      "cognitive_label": "PoorScent",
      "analyst_label": "FollowingScent",
      "analyst_justification": "Analysis error: Invalid control character at: line 5 column 23 (char 97)",
      "critic_label": "PoorScent",
      "critic_agreement": "disagree",
      "critic_justification": "The viewed search results seem to lack relevance or clarity, indicating that the user may not have found any promising scent from the initial query. This aligns with PoorScent, as the user is not engaging with the results meaningfully.",
      "judge_justification": "Judge parsing failed, using critic decision. Error: Invalid control character at: line 5 column 23 (char 98)",
      "confidence_score": 0.6400000000000001,
      "disagreement_score": 0.9949753653258085,
      "flagged_for_review": true,
      "user_override": false,
      "override_version": 1,
      "override_timestamp": "2025-11-19T22:20:08.457354"
    },
    {
      "session_id": "14915_3545",
      "event_id": "14915_3545_qq-1967_cd-7234",
      "timestamp": "2006-04-22 23:25:48",
      "action_type": "CLICK",
      "content": "free porno movies ti ava com",
      "cognitive_label": "PoorScent",
      "analyst_label": "FollowingScent",
      "analyst_justification": "Analysis error: Invalid control character at: line 5 column 23 (char 97)",
      "critic_label": "PoorScent",
      "critic_agreement": "disagree",
      "critic_justification": "Clicking on a result that also lacks clarity suggests that the user is trying to find something but is still navigating through irrelevant or confusing content. This indicates a PoorScent scenario rather than a clear, targeted search.",
      "judge_justification": "Judge parsing failed, using critic decision. Error: Invalid control character at: line 5 column 23 (char 98)",
      "confidence_score": 0.6000000000000001,
      "disagreement_score": 0.9751278549432755,
      "flagged_for_review": true,
      "user_override": false,
      "override_version": 1,
      "override_timestamp": "2025-11-19T22:20:08.457361"
    },
    {
      "session_id": "14915_3545",
      "event_id": "14915_3545_qq-1967",
      "timestamp": "2006-04-22 23:54:17",
      "action_type": "QUERY",
      "content": "tiava",
      "cognitive_label": "PoorScent",
      "analyst_label": "FollowingScent",
      "analyst_justification": "Analysis error: Invalid control character at: line 5 column 23 (char 97)",
      "critic_label": "PoorScent",
      "critic_agreement": "disagree",
      "critic_justification": "The repeated query 'tiava...' indicates a struggle to formulate a relevant search. Given the context of invalid characters and a lack of meaningful progression, this is indicative of PoorScent rather than a well-formed search intent.",
      "judge_justification": "Judge parsing failed, using critic decision. Error: Invalid control character at: line 5 column 23 (char 98)",
      "confidence_score": 0.68,
      "disagreement_score": 0.9220679402351379,
      "flagged_for_review": true,
      "user_override": false,
      "override_version": 1,
      "override_timestamp": "2025-11-19T22:20:08.457368"
    },
    {
      "session_id": "14915_3545",
      "event_id": "14915_3545_qq-1967_serp",
      "timestamp": "2006-04-22 23:54:17",
      "action_type": "SERP_VIEW",
      "content": "Viewed 10 results: ti avas girls com nbsp ti avas girls resources and information, free porno movies ti ava com, free porno movies ti ava com (+7 more)",
      "cognitive_label": "PoorScent",
      "analyst_label": "FollowingScent",
      "analyst_justification": "Analysis error: Invalid control character at: line 5 column 23 (char 97)",
      "critic_label": "PoorScent",
      "critic_agreement": "disagree",
      "critic_justification": "Similar to previous events, the user viewed results that do not seem to meet their needs. The presence of invalid control characters suggests an ongoing lack of clarity or relevance in their query, aligning with PoorScent.",
      "judge_justification": "Judge parsing failed, using critic decision. Error: Invalid control character at: line 5 column 23 (char 98)",
      "confidence_score": 0.6400000000000001,
      "disagreement_score": 0.8611560821533203,
      "flagged_for_review": true,
      "user_override": false,
      "override_version": 1,
      "override_timestamp": "2025-11-19T22:20:08.457374"
    },
    {
      "session_id": "14915_3545",
      "event_id": "14915_3545_qq-1967_cd-7234",
      "timestamp": "2006-04-22 23:54:17",
      "action_type": "CLICK",
      "content": "free porno movies ti ava com",
      "cognitive_label": "PoorScent",
      "analyst_label": "FollowingScent",
      "analyst_justification": "Analysis error: Invalid control character at: line 5 column 23 (char 97)",
      "critic_label": "PoorScent",
      "critic_agreement": "disagree",
      "critic_justification": "Clicking on a poorly formed query result suggests a lack of effective information scent. The user's choice appears to be driven by confusion rather than a clear search strategy, which is characteristic of PoorScent.",
      "judge_justification": "Judge parsing failed, using critic decision. Error: Invalid control character at: line 5 column 23 (char 98)",
      "confidence_score": 0.6000000000000001,
      "disagreement_score": 0.9751113623380661,
      "flagged_for_review": true,
      "user_override": false,
      "override_version": 1,
      "override_timestamp": "2025-11-19T22:20:08.457379"
    }
  ],
  "agent_interactions": [
    {
      "step": 1,
      "agent": "analyst",
      "status": "completed",
      "elapsed_time": 36.00508689880371,
      "decisions": [
        {
          "event_id": "14915_3545_qq-1967",
          "label": "FollowingScent",
          "justification": "Analysis error: Invalid control character at: line 5 column 23 (char 97)",
          "confidence": 0.5
        },
        {
          "event_id": "14915_3545_qq-1967_serp",
          "label": "FollowingScent",
          "justification": "Analysis error: Invalid control character at: line 5 column 23 (char 97)",
          "confidence": 0.5
        },
        {
          "event_id": "14915_3545_qq-1967_cd-7234",
          "label": "FollowingScent",
          "justification": "Analysis error: Invalid control character at: line 5 column 23 (char 97)",
          "confidence": 0.5
        },
        {
          "event_id": "14915_3545_qq-1967",
          "label": "FollowingScent",
          "justification": "Analysis error: Invalid control character at: line 5 column 23 (char 97)",
          "confidence": 0.5
        },
        {
          "event_id": "14915_3545_qq-1967_serp",
          "label": "FollowingScent",
          "justification": "Analysis error: Invalid control character at: line 5 column 23 (char 97)",
          "confidence": 0.5
        },
        {
          "event_id": "14915_3545_qq-1967_cd-7234",
          "label": "FollowingScent",
          "justification": "Analysis error: Invalid control character at: line 5 column 23 (char 97)",
          "confidence": 0.5
        }
      ]
    },
    {
      "step": 2,
      "agent": "critic",
      "status": "completed",
      "elapsed_time": 9.491193771362305,
      "decisions": [
        {
          "event_id": "Event 1",
          "agreement": "disagree",
          "label": "PoorScent",
          "justification": "The user input 'tiava...' appears to be an incomplete or poorly formed query, indicating a lack of clarity in their information need. The presence of an invalid control character suggests confusion or error rather than a targeted search, which aligns more with PoorScent than FollowingScent.",
          "confidence": 0.85
        },
        {
          "event_id": "Event 2",
          "agreement": "disagree",
          "label": "PoorScent",
          "justification": "The viewed search results seem to lack relevance or clarity, indicating that the user may not have found any promising scent from the initial query. This aligns with PoorScent, as the user is not engaging with the results meaningfully.",
          "confidence": 0.8
        },
        {
          "event_id": "Event 3",
          "agreement": "disagree",
          "label": "PoorScent",
          "justification": "Clicking on a result that also lacks clarity suggests that the user is trying to find something but is still navigating through irrelevant or confusing content. This indicates a PoorScent scenario rather than a clear, targeted search.",
          "confidence": 0.75
        },
        {
          "event_id": "Event 4",
          "agreement": "disagree",
          "label": "PoorScent",
          "justification": "The repeated query 'tiava...' indicates a struggle to formulate a relevant search. Given the context of invalid characters and a lack of meaningful progression, this is indicative of PoorScent rather than a well-formed search intent.",
          "confidence": 0.85
        },
        {
          "event_id": "Event 5",
          "agreement": "disagree",
          "label": "PoorScent",
          "justification": "Similar to previous events, the user viewed results that do not seem to meet their needs. The presence of invalid control characters suggests an ongoing lack of clarity or relevance in their query, aligning with PoorScent.",
          "confidence": 0.8
        },
        {
          "event_id": "Event 6",
          "agreement": "disagree",
          "label": "PoorScent",
          "justification": "Clicking on a poorly formed query result suggests a lack of effective information scent. The user's choice appears to be driven by confusion rather than a clear search strategy, which is characteristic of PoorScent.",
          "confidence": 0.75
        }
      ]
    },
    {
      "step": 3,
      "agent": "judge",
      "status": "completed",
      "elapsed_time": 26.12590527534485,
      "decisions": [
        {
          "event_id": "Event 1",
          "final_label": "PoorScent",
          "justification": "Judge parsing failed, using critic decision. Error: Invalid control character at: line 5 column 23 (char 98)",
          "confidence": 0.68,
          "flag_for_review": true,
          "disagreement_score": 0.5
        },
        {
          "event_id": "Event 2",
          "final_label": "PoorScent",
          "justification": "Judge parsing failed, using critic decision. Error: Invalid control character at: line 5 column 23 (char 98)",
          "confidence": 0.6400000000000001,
          "flag_for_review": true,
          "disagreement_score": 0.5
        },
        {
          "event_id": "Event 3",
          "final_label": "PoorScent",
          "justification": "Judge parsing failed, using critic decision. Error: Invalid control character at: line 5 column 23 (char 98)",
          "confidence": 0.6000000000000001,
          "flag_for_review": true,
          "disagreement_score": 0.5
        },
        {
          "event_id": "Event 4",
          "final_label": "PoorScent",
          "justification": "Judge parsing failed, using critic decision. Error: Invalid control character at: line 5 column 23 (char 98)",
          "confidence": 0.68,
          "flag_for_review": true,
          "disagreement_score": 0.5
        },
        {
          "event_id": "Event 5",
          "final_label": "PoorScent",
          "justification": "Judge parsing failed, using critic decision. Error: Invalid control character at: line 5 column 23 (char 98)",
          "confidence": 0.6400000000000001,
          "flag_for_review": true,
          "disagreement_score": 0.5
        },
        {
          "event_id": "Event 6",
          "final_label": "PoorScent",
          "justification": "Judge parsing failed, using critic decision. Error: Invalid control character at: line 5 column 23 (char 98)",
          "confidence": 0.6000000000000001,
          "flag_for_review": true,
          "disagreement_score": 0.5
        }
      ]
    }
  ],
  "num_events": 6,
  "flagged_for_review": true,
  "max_disagreement": 0.9949753653258085
}