{
  "session_id": "19655_4167",
  "job_id": "44cdca32-786d-4fc9-b0cf-b3991122049b",
  "timestamp": "2025-11-20T05:41:13.611326",
  "events": [
    {
      "session_id": "19655_4167",
      "event_id": "19655_4167_qq-2453",
      "timestamp": "2006-05-10 20:14:36",
      "action_type": "QUERY",
      "content": "us buildings",
      "cognitive_label": "PoorScent",
      "analyst_label": "FollowingScent",
      "analyst_justification": "Analysis error: Invalid control character at: line 5 column 23 (char 97)",
      "critic_label": "PoorScent",
      "critic_agreement": "disagree",
      "critic_justification": "The query 'us buildings...' is vague and does not demonstrate a clear intent or targeted information need, which suggests that the user is confused or unsure about what they are searching for. This lack of clarity indicates poor scent rather than a focused search.",
      "judge_justification": "Judge parsing failed, using critic decision. Error: Invalid control character at: line 5 column 23 (char 98)",
      "confidence_score": 0.68,
      "disagreement_score": 1.0012721478939057,
      "flagged_for_review": true,
      "user_override": false,
      "override_version": 1,
      "override_timestamp": "2025-11-20T05:41:39.399808"
    },
    {
      "session_id": "19655_4167",
      "event_id": "19655_4167_qq-2453_serp",
      "timestamp": "2006-05-10 20:14:36",
      "action_type": "SERP_VIEW",
      "content": "Viewed 10 results: www us building materials com, site mason build on us, www us metal buildings com (+7 more)",
      "cognitive_label": "ApproachingSource",
      "analyst_label": "FollowingScent",
      "analyst_justification": "Analysis error: Invalid control character at: line 5 column 23 (char 97)",
      "critic_label": "ApproachingSource",
      "critic_agreement": "disagree",
      "critic_justification": "The user viewed 10 results, which implies they were investigating the information presented. However, the titles and snippets provided do not indicate a strong scent leading to a clear intent. The action of viewing results suggests curiosity rather than a well-formed query, which aligns more with 'ApproachingSource' than 'FollowingScent.'",
      "judge_justification": "Judge parsing failed, using critic decision. Error: Invalid control character at: line 5 column 23 (char 98)",
      "confidence_score": 0.6000000000000001,
      "disagreement_score": 0.9983759082853794,
      "flagged_for_review": true,
      "user_override": false,
      "override_version": 1,
      "override_timestamp": "2025-11-20T05:41:39.399815"
    },
    {
      "session_id": "19655_4167",
      "event_id": "19655_4167_qq-2453_cd-14268",
      "timestamp": "2006-05-10 20:14:36",
      "action_type": "CLICK",
      "content": "us buildings com nbsp this website is for sale nbsp us buildings resources and information",
      "cognitive_label": "PoorScent",
      "analyst_label": "FollowingScent",
      "analyst_justification": "Analysis error: Invalid control character at: line 5 column 23 (char 97)",
      "critic_label": "PoorScent",
      "critic_agreement": "disagree",
      "critic_justification": "The click on a result that states 'this website is for sale' indicates a missed expectation rather than a successful exploration. The content does not fulfill the user's needs and reflects a poor scent, as the user clicked on a link that did not provide the relevant information they were likely seeking.",
      "judge_justification": "Judge parsing failed, using critic decision. Error: Invalid control character at: line 5 column 23 (char 98)",
      "confidence_score": 0.6400000000000001,
      "disagreement_score": 1.0006403982639314,
      "flagged_for_review": true,
      "user_override": false,
      "override_version": 1,
      "override_timestamp": "2025-11-20T05:41:39.399818"
    }
  ],
  "agent_interactions": [
    {
      "step": 1,
      "agent": "analyst",
      "status": "completed",
      "elapsed_time": 11.453489065170288,
      "decisions": [
        {
          "event_id": "19655_4167_qq-2453",
          "label": "FollowingScent",
          "justification": "Analysis error: Invalid control character at: line 5 column 23 (char 97)",
          "confidence": 0.5
        },
        {
          "event_id": "19655_4167_qq-2453_serp",
          "label": "FollowingScent",
          "justification": "Analysis error: Invalid control character at: line 5 column 23 (char 97)",
          "confidence": 0.5
        },
        {
          "event_id": "19655_4167_qq-2453_cd-14268",
          "label": "FollowingScent",
          "justification": "Analysis error: Invalid control character at: line 5 column 23 (char 97)",
          "confidence": 0.5
        }
      ]
    },
    {
      "step": 2,
      "agent": "critic",
      "status": "completed",
      "elapsed_time": 6.622215986251831,
      "decisions": [
        {
          "event_id": "Event 1",
          "agreement": "disagree",
          "label": "PoorScent",
          "justification": "The query 'us buildings...' is vague and does not demonstrate a clear intent or targeted information need, which suggests that the user is confused or unsure about what they are searching for. This lack of clarity indicates poor scent rather than a focused search.",
          "confidence": 0.85
        },
        {
          "event_id": "Event 2",
          "agreement": "disagree",
          "label": "ApproachingSource",
          "justification": "The user viewed 10 results, which implies they were investigating the information presented. However, the titles and snippets provided do not indicate a strong scent leading to a clear intent. The action of viewing results suggests curiosity rather than a well-formed query, which aligns more with 'ApproachingSource' than 'FollowingScent.'",
          "confidence": 0.75
        },
        {
          "event_id": "Event 3",
          "agreement": "disagree",
          "label": "PoorScent",
          "justification": "The click on a result that states 'this website is for sale' indicates a missed expectation rather than a successful exploration. The content does not fulfill the user's needs and reflects a poor scent, as the user clicked on a link that did not provide the relevant information they were likely seeking.",
          "confidence": 0.8
        }
      ]
    },
    {
      "step": 3,
      "agent": "judge",
      "status": "completed",
      "elapsed_time": 7.621742010116577,
      "decisions": [
        {
          "event_id": "Event 1",
          "final_label": "PoorScent",
          "justification": "Judge parsing failed, using critic decision. Error: Invalid control character at: line 5 column 23 (char 98)",
          "confidence": 0.68,
          "flag_for_review": true,
          "disagreement_score": 0.5
        },
        {
          "event_id": "Event 2",
          "final_label": "ApproachingSource",
          "justification": "Judge parsing failed, using critic decision. Error: Invalid control character at: line 5 column 23 (char 98)",
          "confidence": 0.6000000000000001,
          "flag_for_review": true,
          "disagreement_score": 0.5
        },
        {
          "event_id": "Event 3",
          "final_label": "PoorScent",
          "justification": "Judge parsing failed, using critic decision. Error: Invalid control character at: line 5 column 23 (char 98)",
          "confidence": 0.6400000000000001,
          "flag_for_review": true,
          "disagreement_score": 0.5
        }
      ]
    }
  ],
  "num_events": 3,
  "flagged_for_review": true,
  "max_disagreement": 1.0012721478939057
}